Workbook

Sheet Экономика и Сводка
A1: ИНВЕСТИЦИОННЫЙ ДАШБОРД И СВОДКА ПРОЕКТА — ФРУНЗЕ 17
A2: Объект: г. Тула, ул. Фрунзе 17, кв. 76 (2-комн., 43.2 м², 5/5 эт.) | Стратегия: Флиппинг (цикл 2 месяца)
A4: ПОКУПКА ОБЪЕКТА | C4: БЮДЖЕТ РЕМОНТА | D4: ФАКТ ВЛОЖЕНО | E4: ТАРГЕТ ПРОДАЖИ | F4: ПЛАН. ПРИБЫЛЬ | G4: ПЛАН. ROI
A5: 3900000 | C5: ='План vs Рынок (Смета)'!E16 | D5: ='Факт расходов'!F83 | E5: 5600000 | F5: =C17 | G5: =C18
A8: 1. ИНВЕСТИЦИОННАЯ МОДЕЛЬ СДЕЛКИ (ПОЛНАЯ СЕБЕСТОИМОСТЬ И ДОХОДНОСТЬ)
A9: Статья инвестиций / Показатель | B9: Рынок / Базовый план (₽) | C9: Наш план / Факт (₽) | D9: Экономия / Выгода (₽) | E9: Статус | F9: Примечание / Обоснование
A10: 1.1. Стоимость покупки объекта | B10: 3900000 | C10: 3900000 | D10: =B10-C10 | E10: Оплачено | F10: Базовый актив, договор купли-продажи
A11: 1.2. Юр. оформление, пошлина, доступ, IT | B11: 23000 | C11: =SUMIF('Факт расходов'!C5:C82, "*Юр.*", 'Факт расходов'!F5:F82)+SUMIF('Факт расходов'!C5:C82, "*Безопасность*", 'Факт расходов'!F5:F82)+SUMIF('Факт расходов'!C5:C82, "*IT*", 'Факт расходов'!F5:F82)+SUMIF('Факт расходов'!C5:C82, "*Электроэнергия*", 'Факт расходов'!F5:F82) | D11: =B11-C11 | E11: Оплачено | F11: ЭЦП (7к), Росреестр (5к), вскрытие (8к), AI (3к)
A12: 1.3. Бюджет ремонта, стейджинга и клининга | B12: ='План vs Рынок (Смета)'!D16 | C12: ='План vs Рынок (Смета)'!E16 | D12: =B12-C12 | E12: В процессе | F12: Смета по 11 этапам (цель 621 000 ₽ vs рынок 825 000 ₽)
A13: 1.4. Резерв на непредвиденные расходы | B13: 20000 | C13: 0 | D13: =B13-C13 | E13: В резерве | F13: Запас прочности на скрытые дефекты
A14: ИТОГО ПЛАНОВАЯ СЕБЕСТОИМОСТЬ ОБЪЕКТА: | B14: =SUM(B10:B13) | C14: =SUM(C10:C13) | D14: =SUM(D10:D13) | E14: План | F14: Покупка (3.9М) + юристы (23к) + смета ремонта (621к)
A15: ТЕКУЩИЙ ФАКТ ОПЛАЧЕННЫХ СРЕДСТВ НА СЕГОДНЯ: | B15: 3923000 | C15: =C10+C11+C37 | D15: =B15-C15 | E15: Факт | F15: Покупка 3.9М + оформление 23к + факт ремонта 96.7к
A16: ЦЕЛЕВАЯ ВЫРУЧКА ОТ ПРОДАЖИ (ТАРГЕТ): | B16: 5600000 | C16: 5600000 | D16: - | E16: Таргет | F16: 129 630 ₽/м² (верхняя планка Советского р-на)
A17: ПЛАНОВАЯ ЧИСТАЯ ПРИБЫЛЬ ИНВЕСТОРА: | B17: =B16-B14 | C17: =C16-C14 | D17: =C17-B17 | E17: Прибыль | F17: Чистый финансовый результат по итогам проекта
A18: РЕНТАБЕЛЬНОСТЬ ИНВЕСТИЦИЙ (ROI НА ЦИКЛ): | B18: =(B16-B14)/B14 | C18: =C17/C14 | D18: =C18-B18 | E18: ROI | F18: Доходность капитала за 2 месяца
A21: 2. ОПЕРАЦИОННЫЙ ТРЕКЕР БЮДЖЕТА РЕМОНТА (ПЛАН VS ФАКТ VS ОСТАТОК)
A22: Раздел сметы / Вид работ | B22: План сметы (₽) | C22: Факт оплачено (₽) | D22: Остаток к оплате (₽) | E22: Освоено | F22: Статус выполнения | G22: Текущий факт / Примечание
A23: 1. Демонтаж, зачистка, вывоз мусора | B23: ='План vs Рынок (Смета)'!E5 | C23: =SUMIF('Факт расходов'!C5:C82, "*Демонтаж*", 'Факт расходов'!F5:F82) | D23: =B23-C23 | E23: =IFERROR(C23/B23, 0) | F23: В работе | G23: Контейнер 8.5к + сосед 1к + бригада 16к (25.5к)
A24: 2. Входная группа (дверь, доставка, монтаж) | B24: ='План vs Рынок (Смета)'!E6 | C24: =SUMIF('Факт расходов'!C5:C82, "*Двери*", 'Факт расходов'!F5:F82) | D24: =B24-C24 | E24: =IFERROR(C24/B24, 0) | F24: Выполнено | G24: Дверь 16к + доставка 1.5к + монтаж 9к (26.5к под ключ)
A25: 3. Электрика ГОСТ (материалы + работы) | B25: ='План vs Рынок (Смета)'!E7 | C25: =SUMIF('Факт расходов'!C5:C82, "*Электрика*", 'Факт расходов'!F5:F82) | D25: =B25-C25 | E25: =IFERROR(C25/B25, 0) | F25: Разведено / Собрано | G25: Работы 50к + материалы 48.5к (итого 98.5к под ключ)
A26: 4. Сантехника (разводка PPR, ванна 150) | B26: ='План vs Рынок (Смета)'!E8 | C26: =SUMIF('Факт расходов'!C5:C82, "*Сантехника*", 'Факт расходов'!F5:F82) | D26: =B26-C26 | E26: =IFERROR(C26/B26, 0) | F26: Ввод / Стояки | G26: Краны и счётчик 4.1к закрыты, далее трассы
A27: 5. Газ и вентиляция (ВДПО, квитанции, срезка) | B27: 5000 | C27: =SUMIF('Факт расходов'!C5:C82, "*Газ*", 'Факт расходов'!F5:F82) | D27: =B27-C27 | E27: =IFERROR(C27/B27, 0) | F27: Согласование | G27: Акт ВДПО 1.5к + платежки 0.8к закрыты
A28: 6. Перепланировка гардеробной (ГКЛ) | B28: ='План vs Рынок (Смета)'!E9 | C28: 0 | D28: =B28-C28 | E28: =IFERROR(C28/B28, 0) | F28: План | G28: Зашивка двери из зала + проем из спальни
A29: 7. Черновая отделка (полы саморезы, с/у) | B29: ='План vs Рынок (Смета)'!E10 | C29: =SUMIF('Факт расходов'!C5:C82, "*Черновая*", 'Факт расходов'!F5:F82) | D29: =B29-C29 | E29: =IFERROR(C29/B29, 0) | F29: План | G29: Протяжка лаг желтыми саморезами без стяжки
A30: 8. Чистовая отделка (обои греж, ламинат 33кл) | B30: ='План vs Рынок (Смета)'!E11 | C30: =SUMIF('Факт расходов'!C5:C82, "*Чистовая*", 'Факт расходов'!F5:F82) | D30: =B30-C30 | E30: =IFERROR(C30/B30, 0) | F30: План | G30: Единый контур светлый дуб, плинтус 80мм
A31: 9. Натяжные матовые потолки + споты | B31: ='План vs Рынок (Смета)'!E12 | C31: 0 | D31: =B31-C31 | E31: =IFERROR(C31/B31, 0) | F31: План | G31: Матовый сатин, треки/споты по зонам
A32: 10. Межкомнатные двери (3 комплекта) | B32: ='План vs Рынок (Смета)'!E13 | C32: 0 | D32: =B32-C32 | E32: =IFERROR(C32/B32, 0) | F32: План | G32: Белые царговые глухие полотна с магнитными замками
A33: 11. Кухонный гарнитур + колонка Mora | B33: ='План vs Рынок (Смета)'!E14 | C33: 0 | D33: =B33-C33 | E33: =IFERROR(C33/B33, 0) | F33: План | G33: Модульная кухня с интеграцией колонки (заказ Неделя 2)
A34: 12. Стейджинг, освещение, декор, клининг | B34: ='План vs Рынок (Смета)'!E15 | C34: 0 | D34: =B34-C34 | E34: =IFERROR(C34/B34, 0) | F34: План | G34: Минималистичный интерьерный декор под верх планки
A35: 13. Инструмент и расходники (хозмаг/Лемана) | B35: 10000 | C35: =SUMIF('Факт расходов'!C5:C82, "*Инструмент*", 'Факт расходов'!F5:F82)+SUMIF('Факт расходов'!C5:C82, "*Расходные*", 'Факт расходов'!F5:F82)+SUMIF('Факт расходов'!C5:C82, "*Логистика*", 'Факт расходов'!F5:F82) | D35: =B35-C35 | E35: =IFERROR(C35/B35, 0) | F35: В процессе | G35: Лом, мешки, пылесос, перчатки (2 847 ₽)
A36: 14. Мелкие хозрасходы и вспомогательные траты | B36: 5000 | C36: =SUMIF('Факт расходов'!C5:C82, "*Оснащение*", 'Факт расходов'!F5:F82) | D36: =B36-C36 | E36: =IFERROR(C36/B36, 0) | F36: По факту | G36: Расходники для зачистки (300 ₽)
A37: ИТОГО ПО СМЕТЕ РЕМОНТА: | B37: =SUM(B23:B36) | C37: =SUM(C23:C36) | D37: =SUM(D23:D36) | E37: =IFERROR(C37/B37, 0) | F37: В графике | G37: Текущее освоение бюджета
A40: 3. КАРТА ЭКОНОМИИ ИНВЕСТОРА (ОПТИМИЗАЦИЯ УЗЛОВ + СКИДКИ НА ЗАКУПКАХ)
A41: Статья оптимизации / Инженерный узел | B41: Рыночная цена (₽) | C41: Наша цена (₽) | D41: Чистая экономия (₽) | E41: % Выгоды | F41: Обоснование / Способ оптимизации
A42: 3.1. Окна ПВХ (сохранены во всей квартире) | B42: 120000 | C42: 0 | D42: =B42-C42 | E42: =IFERROR(D42/B42, 0) | F42: Сохранены все стеклопакеты и балконный блок (регулировка + откосы)
A43: 3.2. Стояк канализации 110 мм (сохранен) | B43: 15000 | C43: 0 | D43: =B43-C43 | E43: =IFERROR(D43/B43, 0) | F43: Уже заменён на пластик ПВХ/ПП 110мм, перекрытия долбить не нужно
A44: 3.3. Электросчётчик (новый прибор учёта) | B44: 0 | C44: 0 | D44: 0 | E44: =IFERROR(D44/B44, 0) | F44: Новый счётчик закуплен в составе материалов (поз. 17 на 16.5к); распломбировка 2.5к закрыта
A45: 3.4. Фактическая экономия на закупках и работах | B45: ='Факт расходов'!E83 | C45: ='Факт расходов'!F83 | D45: =B45-C45 | E45: =IFERROR(D45/B45, 0) | F45: Скидки от поставщиков (дверь -6к, кабель -2к, мусор -0.5к, демонтаж -4к и др.)
A46: ИТОГО СБЕРЕЖЁННЫЙ КАПИТАЛ ИНВЕСТОРА: | B46: =SUM(B42:B45) | C46: =SUM(C42:C45) | D46: =SUM(D42:D45) | E46: =IFERROR(D46/B46, 0) | F46: Прямой вклад в повышение маржинальности сделки

Sheet Факт расходов
A1: ЖУРНАЛ ФАКТИЧЕСКИХ РАСХОДОВ — ФРУНЗЕ 17
A2: Объект: г. Тула, ул. Фрунзе 17, кв. 76 (2-комн., 43.2 м²) | Флиппинг
A4: № | B4: Дата | C4: Категория | D4: Наименование расхода / Работы | E4: Рыночная цена (₽) | F4: Факт оплачено (₽) | G4: Экономия (₽) | H4: % Экономии | I4: Исполнитель / Поставщик | J4: Примечание / Чек
A5: 1 | B5: 18.08.2026 | C5: Юр. оформление / Торги | D5: Выпуск ЭЦП (электронная цифровая подпись) | E5: 7000 | F5: 7000 | G5: =E5-F5 | H5: =IFERROR(G5/E5, 0) | I5: УЦ / Контур | J5: Для участия в торгах и регистрации
A6: 2 | B6: 18.08.2026 | C6: Юр. оформление / Торги | D6: Государственная пошлина (регистрация права) | E6: 5000 | F6: 5000 | G6: =E6-F6 | H6: =IFERROR(G6/E6, 0) | I6: Росреестр | J6: Госпошлина за переход права
A7: 3 | B7: 18.08.2026 | C7: Безопасность / Доступ | D7: Вскрытие старого замка и обеспечение доступа | E7: 8000 | F7: 8000 | G7: =E7-F7 | H7: =IFERROR(G7/E7, 0) | I7: Служба вскрытия | J7: Аварийное открытие входной двери объекта
A8: 4 | B8: 22.08.2026 | C8: Демонтаж и зачистка | D8: Заказ мусорного контейнера 8 м³ | E8: 9000 | F8: 8500 | G8: =E8-F8 | H8: =IFERROR(G8/E8, 0) | I8: Елена (вывоз мусора) | J8: Вывоз мебели, санузла, чугуна и строительного боя (скидка 500 ₽)
A9: 5 | B9: 22.08.2026 | C9: Демонтаж и зачистка | D9: Аренда/помощь инструментом соседа | E9: 2500 | F9: 1000 | G9: =E9-F9 | H9: =IFERROR(G9/E9, 0) | I9: Сосед по дому | J9: Перфоратор/монтировки/инструмент (экономия 1 500 ₽)
A10: 6 | B10: 22.08.2026 | C10: Расходные материалы | D10: Мешки мусорные плотные, перчатки рабочие | E10: 500 | F10: 300 | G10: =E10-F10 | H10: =IFERROR(G10/E10, 0) | I10: Хозмаг / Рынок | J10: Расходники для сбора и выноса строительного мусора
A11: 7 | B11: 22.08.2026 | C11: Демонтаж и зачистка | D11: Оплата работы бригады (4 чел., 28 чел.-час, спуск с 5 этажа) | E11: 20000 | F11: 16000 | G11: =E11-F11 | H11: =IFERROR(G11/E11, 0) | I11: Бригада разнорабочих | J11: 4 чел., 28 ч.-час, экономия от рынка ~4 000 ₽
A12: 8 | B12: 23.08.2026 | C12: Расходные материалы | D12: Мешки для пылесоса синт. 12л (5 шт) — Леруа/Лемана | E12: 717 | F12: 717 | G12: =E12-F12 | H12: =IFERROR(G12/E12, 0) | I12: ООО Ле Монлид (Лемана ПРО) | J12: Чек 3831 от 23.08.2026 11:05
A13: 9 | B13: 23.08.2026 | C13: Инструмент и расходники | D13: Лом-гвоздодер, мешки 15шт, лента, перчатки 6п, опрыскиватель | E13: 1830 | F13: 1830 | G13: =E13-F13 | H13: =IFERROR(G13/E13, 0) | I13: ООО Ле Монлид (Лемана ПРО) | J13: Чек 3832 от 23.08.2026 11:07
A14: 10 | B14: 23.08.2026 | C14: IT / AI-инфраструктура | D14: Пополнение баланса OpenRouter (AI-ассистент Hermes) | E14: 3000 | F14: 3000 | G14: =E14-F14 | H14: =IFERROR(G14/E14, 0) | I14: OpenRouter | J14: Инфраструктура проектов и аналитики
A15: 11 | B15: 24.08.2026 | C15: Сантехника / Инженерия | D15: Счётчик воды + кран на ввод (материалы) | E15: 2100 | F15: 2100 | G15: =E15-F15 | H15: =IFERROR(G15/E15, 0) | I15: Вадим (сантехник УК) | J15: Покупка материалов для замены закисшей запорной арматуры и счётчика
A16: 12 | B16: 24.08.2026 | C16: Газ / Дымоход | D16: Акт ВДПО — проверка дымохода и вентканала | E16: 1500 | F16: 1500 | G16: =E16-F16 | H16: =IFERROR(G16/E16, 0) | I16: ВДПО / Газовая служба | J16: Обязательная проверка тяги для согласования газа при ремонте
... A73: 69 | B73: 29.09.2026 | C73: Газ / Работы и материалы | D73: Работы газовщика: перенос / срезка / перемонтаж газовой трубы на кухне | E73: 7300 | F73: 7300 | G73: =E73-F73 | H73: =IFERROR(G73/E73, 0) | I73: Газовщик (мастер / горгаз) | J73: Оплата газовщику за перенос/срезку и обвязку газовой трубы на кухне (7 300 ₽)
A74: 70 | B74: 07.10.2026 | C74: Чистовая отделка / Материалы | D74: Материалы для поклейки обоев (обои Twid 12 рул., клей Kleo 4 шт., грунтовка Knauf 10 кг, шпатели, валики, салфетки) | E74: 27045 | F74: 24893 | G74: =E74-F74 | H74: =IF(E74>0;G74/E74;0) | I74: ООО Ле Монлид (Лемана ПРО) | J74: Чек от 07.10.2026 18:25 (касса 4): обои Twid 1.06х10 12 рул. (19 376 ₽ с учетом скидки), грунтовка Knauf 10кг (1 421 ₽), клей Kleo 4 шт. (3 328 ₽), шпатели, салфетки, валик и бюгель. Скидка по промокоду -2 152 ₽
A75: 71 | B75: 07.10.2026 | C75: Логистика и доставка | D75: Такси (доставка / подвоз материалов на объект ул. Фрунзе 17) | E75: 1050 | F75: 1050 | G75: =E75-F75 | H75: =IF(E75>0;G75/E75;0) | I75: Такси | J75: Оперативная доставка материалов и оснащения на объект ул. Фрунзе 17
A76: 72 | B76: 07.10.2026 | C76: Безопасность / Доступ | D76: Ключи от домофона (дубликаты для мастеров и объекта) | E76: 500 | F76: 500 | G76: =E76-F76 | H76: =IF(E76>0;G76/E76;0) | I76: Изготовление ключей | J76: Изготовление комплекта домофонных ключей для доступа рабочих
A77: 73 | B77: 07.10.2026 | C77: Хоз. инвентарь / Оснащение | D77: Зарядка для колонки Xiaomi (оснащение объекта) | E77: 550 | F77: 550 | G77: =E77-F77 | H77: =IF(E77>0;G77/E77;0) | I77: Магазин электроники | J77: Кабель/ЗУ для строительной портативной колонки мастеров
A78: 74 | B78: 08.10.2026 | C78: Чистовая отделка / Работы | D78: Работы плиточника: укладка плитки в санузле, фартук на кухне, фартук ванной из плитки, лючки на магнитах, отверстия под розетки | E78: 86000 | F78: 86000 | G78: =E78-F78 | H78: =IFERROR(G78/E78, 0) | I78: Плиточник (мастер) | J78: Работы плиточника: санузел + фартук на кухне + фартук ванной из плитки + лючки на магнитах + отверстия под розетки. Согласованная оплата 86 000 ₽
A79: 75 | B79: 08.10.2026 | C79: Сантехника / Материалы | D79: Фиттинги для труб «Американка» на трубы ПП на полотенцесушитель | E79: 1600 | F79: 1600 | G79: =E79-F79 | H79: =IFERROR(G79/E79, 0) | I79: Сантехмаркет / Хозмаг | J79: Фиттинги («американки») для подключения полотенцесушителя на ПП-трубы
A80: 76 | B80: 08.10.2026 | C80: Сантехника / Материалы | D80: Зажим для стекла (оснащение санузла) | E80: 800 | F80: 800 | G80: =E80-F80 | H80: =IFERROR(G80/E80, 0) | I80: Хозмаг / Сантехмаркет | J80: Зажим для стекла (крепёж стеклянного экрана/полки в санузле)
A81: 77 | B81: 04.10.2026 | C81: Хоз. инвентарь / Оснащение | D81: Вертикальный пылесос Timberk T-VCH-52 ДР (для финального клининга/стейджинга) | E81: 3200 | F81: 3200 | G81: =E81-F81 | H81: =IFERROR(G81/E81, 0) | I81: Техника Даром (ИП Панин И.П., Тула) | J81: Кассовый чек от 04.10.2026, сохранён в Смета_и_чеки (Чек_ТехникаДаром_Пылесос_Timberk_08.10.2026.jpg). Верхний пылесос для финальной уборки объекта.
A82: 78 | B82: 08.10.2026 | C82: Логистика и доставка | D82: Такси (оперативная поездка по объекту) | E82: 700 | F82: 700 | G82: =E82-F82 | H82: =IFERROR(G82/E82, 0) | I82: Такси | J82: Такси (оперативная поездка по объекту), чек не сохранён.
D83: ИТОГО РАСХОДОВ: | E83: =SUM(E5:E82) | F83: =SUM(F5:F82) | G83: =SUM(G5:G82) | H83: =IFERROR(G83/E83, 0)

Sheet План vs Рынок (Смета)
A1: СМЕТНЫЙ ПЛАН: РЫНОЧНАЯ СТОИМОСТЬ VS ЦЕЛЕВОЙ БЮДЖЕТ
A2: Сравнение среднерыночных цен Тулы с нашей целевой стоимостью выполнения
A4: № | B4: Этап / Раздел работ | C4: Объём / Ед. | D4: Рынок Тула (₽) | E4: Наш план / Цель (₽) | F4: Плановая выгода (₽) | G4: Статус выполнения | H4: Способ оптимизации ниже рынка
A5: 1 | B5: 1. Демонтаж, зачистка стен, вывоз мусора (8м³) | C5: 43.2 м² | D5: 65000 | E5: 45000 | F5: =D5-E5 | G5: В работе | H5: Своими силами / прямые разнорабочие
A6: 2 | B6: 2. Входная дверь металлическая с МДФ + монтаж | C6: 1 шт | D6: 35000 | E6: 25000 | F6: =D6-E6 | G6: План | H6: Оптовый поставщик в Туле
A7: 3 | B7: 3. Электрика ГОСТ ВВГнг-LS (32 точки + щит 18м) | C7: комплекс | D7: 100000 | E7: 75000 | F7: =D7-E7 | G7: ТЗ готово | H7: Трассировка по потолку без лишних штроб
A8: 4 | B8: 4. Сантехника (разводка PPR, инсталляция, ванна 150) | C8: комплекс | D8: 120000 | E8: 90000 | F8: =D8-E8 | G8: План | H8: Стояк уже пластик; прямая закупка сантехники
A9: 5 | B9: 5. Перепланировка гардеробной (зашивка + проём) | C9: комплекс | D9: 30000 | E9: 18000 | F9: =D9-E9 | G9: План | H9: ГКЛ по месту без мокрых процессов
A10: 6 | B10: 6. Черновая отделка (полы саморезы, штукатурка с/у) | C10: 43.2 м² | D10: 95000 | E10: 70000 | F10: =D10-E10 | G10: План | H10: Без заливки стяжки (протяжка лаг)
A11: 7 | B11: 7. Чистовая отделка (обои, ламинат 33кл, плинтус) | C11: 43.2 м² | D11: 140000 | E11: 110000 | F11: =D11-E11 | G11: План | H11: Светлый сканди-стандарт, единый контур
A12: 8 | B12: 8. Натяжные матовые потолки + споты (вся кв.) | C12: 43.2 м² | D12: 45000 | E12: 35000 | F12: =D12-E12 | G12: План | H12: Прямой замер от бригады потолочников
A13: 9 | B13: 9. Межкомнатные двери (3 шт глухие + доборы) | C13: 3 компл | D13: 50000 | E13: 38000 | F13: =D13-E13 | G13: План | H13: Светлые царговые полотна с магнитными замками
A14: 10 | B14: 10. Кухонный гарнитур + фартук + мойка/смеситель | C14: 1 компл | D14: 95000 | E14: 75000 | F14: =D14-E14 | G14: План | H14: Модульная кухня с интеграцией колонки Mora
A15: 11 | B15: 11. Стейджинг, освещение, декор, клининг | C15: комплекс | D15: 50000 | E15: 40000 | F15: =D15-E15 | G15: План | H15: Минималистичный интерьерный декор
B16: ИТОГО СМЕТА РЕМОНТА: | D16: =SUM(D5:D15) | E16: =SUM(E5:E15) | F16: =SUM(F5:F15)

Sheet База материалов (Комплектация)
A1: ГЕНЕРАЛЬНАЯ МАТРИЦА БЮДЖЕТА И КОМПЛЕКТАЦИИ (630 657,80 ₽)
A2: Полная структура расходов Фрунзе 17 | Точная сверка с листом «Факт расходов» (1-в-1 до копейки, все 78 позиций)
A3: 💡 Используй значки [-] и [+] для сворачивания блоков (Материалы, Спецпоставщики, Работы, Юр. расходы)
A4: № в Факте | B4: Зона / Помещение | C4: Категория | D4: Наименование расхода | E4: Артикул / Код | F4: Ед. изм. | G4: Кол-во | H4: Цена / ед. (₽) | I4: Сумма (₽) | J4: Поставщик / Подрядчик | K4: Ссылка / Документ | L4: Примечание / Назначение
B5: 🛁 БЛОК 1: СТРОИТЕЛЬНЫЕ И ЧИСТОВЫЕ МАТЕРИАЛЫ «ЛЕМАНА ПРО» (27 ЧЕКОВ)
A6: 8 | B6: Расходники | C6: Пылесос | D6: Мешки для пылесоса синт. 12л (5 шт) — Леруа/Лемана | E6: 4607086338088 | F6: упак. | G6: 1 | H6: 717 | I6: =G6*H6 | J6: ООО Ле Монлид (Лемана ПРО) | K6: =HYPERLINK("https://lemanapro.ru/search/?q=мешки+для+пылесоса+12л", "Открыть ↗")
A7: 9 | B7: Инструмент | C7: Демонтаж | D7: Лом-гвоздодер, мешки 15шт, лента, перчатки 6п, опрыскиватель | E7: 4603333000001 | F7: компл. | G7: 1 | H7: 1830 | I7: =G7*H7 | J7: ООО Ле Монлид (Лемана ПРО) | K7: =HYPERLINK("https://lemanapro.ru/search/?q=лом+гвоздодер", "Открыть ↗")
A8: 25 | B8: Черновые стены | C8: Шпатлевка / Грунт | D8: Материалы для зачистки и грунтования (шпатлевка 20кг, грунт 10л, СТ99, фильтр Rommer) | E8: 3276006224277 | F8: компл. | G8: 1 | H8: 4803.6 | I8: =G8*H8 | J8: ООО Ле Монлид (Лемана ПРО) | K8: =HYPERLINK("https://lemanapro.ru/search/?q=грунт+axton+10л", "Открыть ↗")
A9: 26 | B9: Инструмент | C9: Ёмкости | D9: Ведро строительное круглое 20 л (2 шт.) | E9: 4610008470475 | F9: шт. | G9: 2 | H9: 128 | I9: =G9*H9 | J9: ООО Ле Монлид (Лемана ПРО) | K9: =HYPERLINK("https://lemanapro.ru/search/?q=ведро+строительное+20л", "Открыть ↗")
A10: 28 | B10: Черновые стены | C10: Шпатлевка / Шпатели | D10: Материалы для подготовки стен (грунт Axton 10л 4шт, шпатлевка 20кг 2шт, шпатели, мешки) | E10: 4601745004252 | F10: компл. | G10: 1 | H10: 3308 | I10: =G10*H10 | J10: ООО Ле Монлид (Лемана ПРО) | K10: =HYPERLINK("https://lemanapro.ru/search/?q=шпатлевка+старатели+20кг", "Открыть ↗")
A11: 30 | B11: Черновые стены | C11: Штукатурка / Бетонконтакт | D11: Материалы штукатурки и шпаклёвки (Бетонконтакт 12кг 3шт, финиш 5шт, штукатурка 3шт, правило, углы) | E11: 4607017518816 | F11: компл. | G11: 1 | H11: 8162 | I11: =G11*H11 | J11: ООО Ле Монлид (Лемана ПРО) | K11: =HYPERLINK("https://lemanapro.ru/search/?q=бетонконтакт+axton+12кг", "Открыть ↗")
A12: 32 | B12: Черновые стены | C12: Шпаклёвка | D12: Материалы штукатурки и шпаклёвки (шпатлевка финиш 20кг, штукатурка 30кг 2шт, перчатки) | E12: 4601745002814 | F12: компл. | G12: 1 | H12: 1594 | I12: =G12*H12 | J12: ООО Ле Монлид (Лемана ПРО) | K12: =HYPERLINK("https://lemanapro.ru/search/?q=шпатлевка+финишная+старатели", "Открыть ↗")
A13: 34 | B13: Санузел | C13: Санфаянс / Смесители | D13: Сантехника и санфаянс с/у (ванна Нерея 150, каркас Sensea, унитаз Sanita, раковина 60, смесители 2шт, душ, сифон) | E13: 4600779023659 | F13: компл. | G13: 1 | H13: 30021 | I13: =G13*H13 | J13: ООО Ле Монлид (Лемана ПРО) | K13: =HYPERLINK("https://lemanapro.ru/search/?q=%D0%92%D0%B0%D0%BD%D0%BD%D0%B0+%D0%9D%D0%B5%D1%80%D0%B5%D1%8F+150%D1%8570+%D0%B0%D0%BA%D1%80%D0%B8%D0%BB%D0%BE%D0%B2%D0%B0%D1%8F", "Открыть ↗")
A14: 35 | B14: Санузел | C14: Керамогранит / Затирка | D14: Керамогранит Calacatta 60х120 (14 упак. / 20.16 м²) + затирка Ceresit CE 40 2кг 2шт | E14: 4673766221451 | F14: компл. | G14: 1 | H14: 33457 | I14: =G14*H14 | J14: ООО Ле Монлид (Лемана ПРО) | K14: =HYPERLINK("https://lemanapro.ru/search/?q=%D0%9A%D0%B5%D1%80%D0%B0%D0%BC%D0%BE%D0%B3%D1%80%D0%B0%D0%BD%D0%B8%D1%82+Calacatta+60%D1%85120", "Открыть ↗")
A15: 36 | B15: Санузел | C15: Плиточный клей | D15: Плиточный клей Unis 2000 C1T 25 кг для формата 60х120 (13 мешков) | E15: 4607005180063 | F15: мешок | G15: 13 | H15: 382.53846 | I15: =G15*H15 | J15: ООО Ле Монлид (Лемана ПРО) | K15: =HYPERLINK("https://lemanapro.ru/search/?q=%D0%9F%D0%BB%D0%B8%D1%82%D0%BE%D1%87%D0%BD%D1%8B%D0%B9+%D0%BA%D0%BB%D0%B5%D0%B9+Unis+2000+C1T", "Открыть ↗")
A16: 37 | B16: Санузел | C16: СВП | D16: Система выравнивания плитки СВП DILWIS (зажимы 1 мм 200 шт, клинья 100 шт) | E16: 4610085150475 | F16: компл. | G16: 1 | H16: 853 | I16: =G16*H16 | J16: ООО Ле Монлид (Лемана ПРО) | K16: =HYPERLINK("https://lemanapro.ru/search/?q=%D0%A1%D0%92%D0%9F+DILWIS+%D0%B7%D0%B0%D0%B6%D0%B8%D0%BC%D1%8B+%D0%B4%D0%BB%D1%8F+%D0%BF%D0%BB%D0%B8%D1%82%D0%BA%D0%B8", "Открыть ↗")
A17: 38 | B17: Черновые стены | C17: Шпаклёвка | D17: Материалы для штукатурки и шпаклёвки (повторный добор: финиш 20кг, штукатурка 2шт) | E17: 4601745000407 | F17: компл. | G17: 1 | H17: 1594 | I17: =G17*H17 | J17: ООО Ле Монлид (Лемана ПРО) | K17: =HYPERLINK("https://lemanapro.ru/search/?q=штукатурка+старатели+30кг", "Открыть ↗")
A18: 39 | B18: Санузел | C18: Стяжка / Короба | D18: Материалы для стяжки пола и короба с/у (пескобетон М-300 6шт, Knauf 50х40, ГСП 2шт, фибра, саморезы, стамеска) | E18: 4610007550932 | F18: компл. | G18: 1 | H18: 3182.67 | I18: =G18*H18 | J18: ООО Ле Монлид (Лемана ПРО) | K18: =HYPERLINK("https://lemanapro.ru/search/?q=пескобетон+м300", "Открыть ↗")
A19: 45 | B19: Санузел | C19: Черновые стены / Гидроизоляция | D19: Штукатурка Старатели 8шт, гидроизоляция Unis 4кг, люк Fonet 200х250, маяки, профиль, фитинги, рулетки | E19: 4601745000407 | F19: компл. | G19: 1 | H19: 7827.6 | I19: =G19*H19 | J19: ООО Ле Монлид (Лемана ПРО) | K19: =HYPERLINK("https://lemanapro.ru/search/?q=%D0%A8%D1%82%D1%83%D0%BA%D0%B0%D1%82%D1%83%D1%80%D0%BA%D0%B0+%D0%B3%D0%B8%D0%BF%D1%81%D0%BE%D0%B2%D0%B0%D1%8F+%D0%A1%D1%82%D0%B0%D1%80%D0%B0%D1%82%D0%B5%D0%BB%D0%B8+30%D0%BA%D0%B3", "Открыть ↗")
A20: 46 | B20: Все зоны | C20: Радиаторы / Трубы | D20: Эмаль аэрозольная Luxens белая сатиновая и матовая 520 мл (2 шт.) | E20: 3276007227604 | F20: компл. | G20: 1 | H20: 648 | I20: =G20*H20 | J20: ООО Ле Монлид (Лемана ПРО) | K20: =HYPERLINK("https://lemanapro.ru/search/?q=%D0%AD%D0%BC%D0%B0%D0%BB%D1%8C+%D0%B0%D1%8D%D1%80%D0%BE%D0%B7%D0%BE%D0%BB%D1%8C%D0%BD%D0%B0%D1%8F+Luxens+%D0%B1%D0%B5%D0%BB%D0%B0%D1%8F+%D1%81%D0%B0%D1%82%D0%B8%D0%BD%D0%BE%D0%B2%D0%B0%D1%8F", "Открыть ↗")
A21: 47 | B21: Санузел | C21: Стяжка / Добавки | D21: Ускоритель твердения Cemfix для стяжки пола, 1 литр (добавка в пескобетон М300) | E21: 4650068600092 | F21: шт. | G21: 1 | H21: 262 | I21: =G21*H21 | J21: ООО Ле Монлид (Лемана ПРО) | K21: =HYPERLINK("https://lemanapro.ru/search/?q=%D0%A3%D1%81%D0%BA%D0%BE%D1%80%D0%B8%D1%82%D0%B5%D0%BB%D1%8C+%D1%82%D0%B2%D0%B5%D1%80%D0%B4%D0%B5%D0%BD%D0%B8%D1%8F+Cemfix", "Открыть ↗")
A22: 50 | B22: Санузел | C22: Расходники / Инструмент | D22: Пистолет для герметика скелетный + герметик санитарный силиконовый (Лемана ПРО) | E22: 82420455 | F22: компл. | G22: 1 | H22: 650 | I22: =G22*H22 | J22: ООО Ле Монлид (Лемана ПРО) | K22: =HYPERLINK("https://lemanapro.ru/search/?q=пистолет+для+герметика", "Открыть ↗")
A23: 51 | B23: Санузел / Стены | C23: Штукатурка / Мешки | D23: Штукатурка гипсовая Старатели 30кг 3шт, перчатки, мешки 3шт (Лемана ПРО) | E23: 4601745000407 | F23: компл. | G23: 1 | H23: 1638 | I23: =G23*H23 | J23: ООО Ле Монлид (Лемана ПРО) | K23: =HYPERLINK("https://lemanapro.ru/search/?q=%D0%A8%D1%82%D1%83%D0%BA%D0%B0%D1%82%D1%83%D1%80%D0%BA%D0%B0+%D0%B3%D0%B8%D0%BF%D1%81%D0%BE%D0%B2%D0%B0%D1%8F+%D0%A1%D1%82%D0%B0%D1%80%D0%B0%D1%82%D0%B5%D0%BB%D0%B8+30%D0%BA%D0%B3", "Открыть ↗")
A24: 52 | B24: Радиаторы / Стены | C24: Краска / Кисти | D24: Грунт-эмаль Luxens 3в1 белая 2.4кг, щетка металл 5-рядная, кисть Dilwis 70мм | E24: 4610088004195 | F24: компл. | G24: 1 | H24: 1769 | I24: =G24*H24 | J24: ООО Ле Монлид (Лемана ПРО) | K24: =HYPERLINK("https://lemanapro.ru/search/?q=%D0%93%D1%80%D1%83%D0%BD%D1%82+%D1%8D%D0%BC%D0%B0%D0%BB%D1%8C+Luxens+3%D0%B21+%D0%B1%D0%B5%D0%BB%D0%B0%D1%8F", "Открыть ↗")
A25: 53 | B25: Санузел / Короб | C25: Профиль / Саморезы | D25: Профиль ППН 27х28 3шт, профиль ПП 60х27 1шт, саморезы оцинк./фосфат. (Лемана ПРО) | E25: 4600776027292 | F25: компл. | G25: 1 | H25: 911.7 | I25: =G25*H25 | J25: ООО Ле Монлид (Лемана ПРО) | K25: =HYPERLINK("https://lemanapro.ru/search/?q=%D0%9F%D1%80%D0%BE%D1%84%D0%B8%D0%BB%D1%8C+%D0%9F%D0%9F+60%D1%8527+Knauf", "Открыть ↗")
A26: 54 | B26: Санузел / Короб | C26: ГСП / Профиль / Смеси | D26: ГСП-Н3 Knauf влагост. 1500х600х12.5 2шт, штукатурка Старатели 30кг, профили 28х27 2шт, 60х27 1шт | E26: 4607160003634 | F26: компл. | G26: 1 | H26: 1582 | I26: =G26*H26 | J26: ООО Ле Монлид (Лемана ПРО) | K26: =HYPERLINK("https://lemanapro.ru/search/?q=%D0%93%D0%A1%D0%9F+%D0%9D3+Knauf+%D0%B2%D0%BB%D0%B0%D0%B3%D0%BE%D1%81%D1%82%D0%BE%D0%B9%D0%BA%D0%B8%D0%B9", "Открыть ↗")
A27: 55 | B27: Полы / Финиш | C27: Ламинат / Плинтус | D27: Ламинат Kronostep Дуб Ночиолла 33кл 10мм 24 упак./41.52м², подложка Monlid 9шт, плинтус белый 8см 20шт | E27: 4607113367721 | F27: компл. | G27: 1 | H27: 41914.52 | I27: =G27*H27 | J27: ООО Ле Монлид (Лемана ПРО) | K27: =HYPERLINK("https://lemanapro.ru/search/?q=%D0%9B%D0%B0%D0%BC%D0%B8%D0%BD%D0%B0%D1%82+Kronostep+%D0%94%D1%83%D0%B1+%D0%9D%D0%BE%D1%87%D0%B8%D0%BE%D0%BB%D0%BB%D0%B0+33+%D0%BA%D0%BB%D0%B0%D1%81%D1%81+10%D0%BC%D0%BC", "Открыть ↗")
A28: 56 | B28: Стены / Потолок | C28: Грунт / Клей | D28: Грунт перекрывающий пятна Axton 1л, клей монтажный Kudo 2шт, валик нат. мех, макловица-мини | E28: 4690364027858 | F28: компл. | G28: 1 | H28: 1070 | I28: =G28*H28 | J28: ООО Ле Монлид (Лемана ПРО) | K28: =HYPERLINK("https://lemanapro.ru/search/?q=%D0%93%D1%80%D1%83%D0%BD%D1%82+%D0%BF%D0%B5%D1%80%D0%B5%D0%BA%D1%80%D1%8B%D0%B2%D0%B0%D1%8E%D1%89%D0%B8%D0%B9+%D0%BF%D1%8F%D1%82%D0%BD%D0%B0+Axton", "Открыть ↗")
A29: 57 | B29: Хознужды / Инструмент | C29: Уборка / Краска | D29: Швабра In Loran, тряпки 3шт, краска Olimp 0.9л, упак. лента Axton, саморезы, ножи 2шт, карандаш | E29: 4630085515241 | F29: компл. | G29: 1 | H29: 1707.17 | I29: =G29*H29 | J29: ООО Ле Монлид (Лемана ПРО) | K29: =HYPERLINK("https://lemanapro.ru/search/?q=%D0%9A%D1%80%D0%B0%D1%81%D0%BA%D0%B0+%D0%9E%D0%BB%D0%B8%D0%BC%D0%BF+%D1%84%D0%B0%D1%81%D0%B0%D0%B4%D0%BD%D0%B0%D1%8F+%D0%B1%D0%B5%D0%BB%D0%B0%D1%8F", "Открыть ↗")
A30: 65 | B30: Санузел / Инженерия | C30: Трубы / Фитинги / Биты | D30: Труба ПП D20 2шт, отвод 50х15°, соединитель D50, биты Rage PH2 70мм | E30: 4607181620858 | F30: компл. | G30: 1 | H30: 550 | I30: =G30*H30 | J30: ООО Ле Монлид (Лемана ПРО) | K30: =HYPERLINK("https://lemanapro.ru/search/?q=%D0%A2%D1%80%D1%83%D0%B1%D0%B0+%D0%BF%D0%BE%D0%BB%D0%B8%D0%BF%D1%80%D0%BE%D0%BF%D0%B8%D0%BB%D0%B5%D0%BD%D0%BE%D0%B2%D0%B0%D1%8F+20+%D0%BC%D0%BC+Valtec", "Открыть ↗")
A31: 66 | B31: Санузел / Финиш | C31: Керамогранит Calacatta | D31: Керамогранит Calacatta superwhite 60х120 (добор 2 упак. / 2.88 м²) | E31: 4673766221451 | F31: упак. | G31: 2 | H31: 2938 | I31: =G31*H31 | J31: ООО Ле Монлид (Лемана ПРО) | K31: =HYPERLINK("https://lemanapro.ru/search/?q=%D0%9A%D0%B5%D1%80%D0%B0%D0%BC%D0%BE%D0%B3%D1%80%D0%B0%D0%BD%D0%B8%D1%82+Calacatta+60%D1%85120", "Открыть ↗")
A32: 70 | B32: Все зоны / Стены | C32: Обои / Чистовая отделка | D32: Материалы для поклейки обоев (обои Twid 12 рул., клей Kleo 4 шт., грунтовка Knauf 10 кг, шпатели, валики, салфетки) | E32: 4607160007070 | F32: компл. | G32: 1 | H32: 24893 | I32: =G32*H32 | J32: ООО Ле Монлид (Лемана ПРО) | K32: =HYPERLINK("https://lemanapro.ru/search/?q=%D0%9E%D0%B1%D0%BE%D0%B8+%D0%B2%D0%B8%D0%BD%D0%B8%D0%BB%D0%BE%D0%B2%D1%8B%D0%B5+%D0%BD%D0%B0+%D1%84%D0%BB%D0%B8%D0%B7%D0%B5%D0%BB%D0%B8%D0%BD%D0%B5+1.06+Twid", "Открыть ↗")
B33: ИТОГО МАТЕРИАЛЫ ЛЕМАНА ПРО (ПО ЧЕКАМ): | I33: =SUM(I6:I32)
B34: ⚡ БЛОК 2: ИНЖЕНЕРНЫЕ МАТЕРИАЛЫ, ДВЕРИ И ОСНАЩЕНИЕ (СПЕЦПОСТАВЩИКИ) (21 ПОЗИЦИЙ)
A35: 6 | B35: Расходники | C35: Демонтаж | D35: Мешки мусорные плотные, перчатки рабочие (хозмаг/рынок) | E35: ХОЗМАГ-МЕШКИ | F35: компл. | G35: 1 | H35: 300 | I35: =G35*H35 | J35: Хозмаг / Рынок | K35: =HYPERLINK("https://www.avito.ru/tula/remont_i_stroitelstvo?q=мешки+мусорные+строительные", "Открыть ↗")
A36: 11 | B36: Сантехника | C36: Учёт воды | D36: Счётчик горячей/холодной воды + кран на ввод (материалы) | E36: СЧЕТЧИК-ВОДЫ | F36: компл. | G36: 1 | H36: 2100 | I36: =G36*H36 | J36: Вадим (сантехник УК) | K36: =HYPERLINK("https://lemanapro.ru/search/?q=счетчик+воды+универсальный", "Открыть ↗")
A37: 14 | B37: Сантехника | C37: Учёт воды | D37: Покупка и установка счётчика и кранов (доплата за фитинги и муфты) | E37: ФИТИНГИ-САНТЕХ | F37: компл. | G37: 1 | H37: 2000 | I37: =G37*H37 | J37: Вадим (сантехник УК) | K37: =HYPERLINK("https://lemanapro.ru/search/?q=шаровый+кран+1/2", "Открыть ↗")
A38: 15 | B38: Входная группа | C38: Двери | D38: Покупка входной металлической двери с внутренней МДФ-панелью | E38: ДВЕРЬ-ВХОД-МДФ | F38: шт. | G38: 1 | H38: 16000 | I38: =G38*H38 | J38: Владимир (двери) | K38: =HYPERLINK("https://www.avito.ru/tula/remont_i_stroitelstvo?q=входная+металлическая+дверь+мдф", "Открыть ↗")
A39: 16 | B39: Входная группа | C39: Логистика | D39: Доставка входной металлической двери на объект | E39: ДОСТАВКА-ДВЕРЬ | F39: рейс | G39: 1 | H39: 1500 | I39: =G39*H39 | J39: Владимир / Доставка | K39: =HYPERLINK("https://www.avito.ru/tula/predlozheniya_uslug?q=доставка+дверей+грузоперевозки", "Открыть ↗")
A40: 17 | B40: Электрика | C40: Щит / Автоматика | D40: Черновые материалы электрики (щит 18м, новый электросчётчик, автоматы, УЗО, гофра) | E40: ЩИТ-АВТ-КОМПЛЕКТ | F40: компл. | G40: 1 | H40: 16500 | I40: =G40*H40 | J40: Анатолий / Поставщик | K40: =HYPERLINK("https://lemanapro.ru/search/?q=щит+встраиваемый+18+модулей", "Открыть ↗")
A41: 19 | B41: Электрика | C41: Кабель | D41: Кабель силовой ВВГнг-LS (ГОСТ 3х2.5 и 3х1.5 для всех трасс) | E41: ВВГнг-LS-ГОСТ-1 | F41: бухта | G41: 1 | H41: 18000 | I41: =G41*H41 | J41: Электромонтаж / Поставщик | K41: =HYPERLINK("https://lemanapro.ru/search/?q=кабель+ВВГнг-LS+3х2.5", "Открыть ↗")
A42: 20 | B42: Электрика | C42: Крепёж | D42: Стяжки нейлоновые и крепёж для монтажа кабеля | E42: КРЕПЕЖ-КАБЕЛЬ | F42: компл. | G42: 1 | H42: 1000 | I42: =G42*H42 | J42: Хозмаг / Электромонтаж | K42: =HYPERLINK("https://lemanapro.ru/search/?q=дюбель+хомут+для+кабеля", "Открыть ↗")
A43: 23 | B43: Электрика | C43: Кабель | D43: Докупка силового кабеля ВВГнг-LS (дополнительный метраж трасс) | E43: ВВГнг-LS-ГОСТ-2 | F43: бухта | G43: 1 | H43: 13000 | I43: =G43*H43 | J43: Электромонтаж / Поставщик | K43: =HYPERLINK("https://lemanapro.ru/search/?q=кабель+ВВГнг-LS+3х1.5", "Открыть ↗")
A44: 27 | B44: Оснащение | C44: Инвентарь | D44: Портативная акустика Xiaomi Bluetooth Speaker Essential Green | E44: XIAOMI-SPK-ESS | F44: шт. | G44: 1 | H44: 1250 | I44: =G44*H44 | J44: ООО ДНС Ритейл (DNS) | K44: =HYPERLINK("https://www.dns-shop.ru/search/?q=Xiaomi+Bluetooth+Speaker", "Открыть ↗")
A45: 29 | B45: Оснащение | C45: Хознужды | D45: Хозрасходы на объект: салфетки влажные и питьевая вода для мастеров | E45: ХОЗ-ВОДА-САЛФЕТКИ | F45: компл. | G45: 1 | H45: 520 | I45: =G45*H45 | J45: Хозмаг / Продукты | K45: =HYPERLINK("https://www.avito.ru/tula/produkty_pitaniya?q=питьевая+вода+19л", "Открыть ↗")
A46: 43 | B46: Санузел | C46: Канализация | D46: Канализация с/у (муфта-восстановитель раструба 110/110, трубы ПП 50, тройник 110/50, заглушка, отводы) | E46: КАНАЛ-СУ-110-50 | F46: компл. | G46: 1 | H46: 2988 | I46: =G46*H46 | J46: ИП Кучеров М.И. (Полимерстрой) | K46: =HYPERLINK("https://www.avito.ru/tula/remont_i_stroitelstvo?q=восстановитель+раструба+110", "Открыть ↗")
A47: 44 | B47: Санузел / Кухня | C47: Водоснабжение | D47: Трубы армированные Faser 20х2.8 12м, настенная планка смесителя, кран DN15, муфты, клипсы | E47: PPR-FASER-WATSON | F47: компл. | G47: 1 | H47: 3139.54 | I47: =G47*H47 | J47: ТС «Ваттсон» (Центргазсервис) | K47: =HYPERLINK("https://wattson.ru/search/?q=Faser+20", "Открыть ↗")
A48: 58 | B48: Электрика | C48: Материалы / Розетки | D48: Электротовары (комплектующие/расходники электрики, ул. Коминтерна 26) | E48: ЭЛЕКТРО-КОМИНТЕРНА | F48: компл. | G48: 1 | H48: 190 | I48: =G48*H48 | J48: Магазин «Электротовары» | K48: =HYPERLINK("https://www.avito.ru/tula/remont_i_stroitelstvo?q=электротовары+коминтерна", "Открыть ↗")
A49: 59 | B49: Санузел | C49: СВП / Клинья | D49: Клинья для плитки СВП 32х8х9мм 50шт (Магазин крепежа, ул. Мосина 29) | E49: СВП-КЛИНЬЯ-50 | F49: упак. | G49: 1 | H49: 210 | I49: =G49*H49 | J49: ИП Звягинцева С.Н. (Крепеж) | K49: =HYPERLINK("https://www.avito.ru/tula/remont_i_stroitelstvo?q=клинья+для+плитки+свп", "Открыть ↗")
A50: 64 | B50: Отопление | C50: Краны радиаторов | D50: Два крана на радиаторы отопления (запорно-регулировочные краны) | E50: КРАНЫ-РАДИАТОР-2 | F50: компл. | G50: 1 | H50: 1100 | I50: =G50*H50 | J50: Сантехмаркет / Хозмаг | K50: =HYPERLINK("https://lemanapro.ru/search/?q=кран+для+радиатора+отопления", "Открыть ↗")
A51: 67 | B51: Санузел / Плитка | C51: Уголки для плитки | D51: Уголки для плитки (Михаил) | E51: УГОЛКИ-ПЛИТКА | F51: компл. | G51: 1 | H51: 260 | I51: =G51*H51 | J51: Михаил (мастер/плиточник) | K51: =HYPERLINK("https://www.avito.ru/tula/remont_i_stroitelstvo?q=уголки+для+плитки", "Открыть ↗")
A52: 73 | B52: Оснащение | C52: Инвентарь | D52: Зарядка для колонки Xiaomi (оснащение объекта) | E52: ЗУ-XIAOMI-TYPEC | F52: шт. | G52: 1 | H52: 550 | I52: =G52*H52 | J52: Магазин электроники | K52: =HYPERLINK("https://www.dns-shop.ru/search/?q=%D0%B7%D0%B0%D1%80%D1%8F%D0%B4%D0%BD%D0%BE%D0%B5+%D1%83%D1%81%D1%82%D1%80%D0%BE%D0%B9%D1%81%D1%82%D0%B2%D0%BE+Type+C+20W", "Открыть ↗")
A53: 75 | B53: Санузел | C53: Сантехника / Материалы | D53: Фиттинги для труб «Американка» на трубы ПП на полотенцесушитель | E53: ФИТТИНГИ-АМЕРИКАНКА | F53: компл. | G53: 1 | H53: 1600 | I53: =G53*H53 | J53: Сантехмаркет / Хозмаг | K53: =HYPERLINK("https://www.avito.ru/tula/predlozheniya_uslug?q=фитинги+американка+для+труб", "Открыть ↗")
A54: 76 | B54: Санузел | C54: Сантехника / Материалы | D54: Зажим для стекла (оснащение санузла) | E54: ЗАЖИМ-СТЕКЛО-СУ | F54: шт. | G54: 1 | H54: 800 | I54: =G54*H54 | J54: Хозмаг / Сантехмаркет | K54: =HYPERLINK("https://www.avito.ru/tula/predlozheniya_uslug?q=зажим+для+стекла+санузел", "Открыть ↗")
A55: 77 | B55: Оснащение | C55: Инвентарь | D55: Вертикальный пылесос Timberk T-VCH-52 ДР (для финального клининга/стейджинга) | E55: TIMBERK-TVCH52 | F55: шт. | G55: 1 | H55: 3200 | I55: =G55*H55 | J55: Техника Даром (ИП Панин И.П., Тула) | K55: =HYPERLINK("https://www.dns-shop.ru/search/?q=Timberk+T-VCH-52", "Открыть ↗")
B56: ИТОГО МАТЕРИАЛЫ СПЕЦПОСТАВЩИКОВ: | I56: =SUM(I35:I55)
B57: 👷‍♂️ БЛОК 3: РАБОТЫ МАСТЕРОВ, ОТДЕЛКА, ДЕМОНТАЖ И ЛОГИСТИКА (20 ПОЗИЦИЙ)
A58: 3 | B58: Безопасность | C58: Вскрытие | D58: Вскрытие старого замка и обеспечение первого доступа | E58: ВСКРЫТИЕ-ЗАМКА | F58: выезд | G58: 1 | H58: 8000 | I58: =G58*H58 | J58: Служба вскрытия | K58: =HYPERLINK("https://www.avito.ru/tula/predlozheniya_uslug?q=вскрытие+замков", "Открыть ↗")
A59: 4 | B59: Демонтаж | C59: Вывоз мусора | D59: Заказ мусорного контейнера 8 м³ (лодочка) | E59: КОНТЕЙНЕР-МУСОР-8М3 | F59: рейс | G59: 1 | H59: 8500 | I59: =G59*H59 | J59: Елена (вывоз мусора) | K59: =HYPERLINK("https://www.avito.ru/tula/predlozheniya_uslug?q=вывоз+мусора+контейнер+8+м3", "Открыть ↗")
A60: 5 | B60: Демонтаж | C60: Аренда | D60: Аренда инструмента и помощь соседа по дому | E60: АРЕНДА-ИНСТРУМЕНТ | F60: услуга | G60: 1 | H60: 1000 | I60: =G60*H60 | J60: Сосед по дому | K60: =HYPERLINK("https://www.avito.ru/tula/predlozheniya_uslug?q=аренда+перфоратора", "Открыть ↗")
A61: 7 | B61: Демонтаж | C61: Работы | D61: Оплата работы бригады разнорабочих (4 чел., 28 чел.-час, спуск с 5 этажа) | E61: ДЕМОНТАЖ-БРИГАДА-1 | F61: смена | G61: 1 | H61: 16000 | I61: =G61*H61 | J61: Бригада разнорабочих | K61: =HYPERLINK("https://www.avito.ru/tula/predlozheniya_uslug?q=демонтаж+квартиры+разнорабочие", "Открыть ↗")
A62: 18 | B62: Входная группа | C62: Монтаж | D62: Монтаж входной двери (демонтаж 2 старых дверей + монтаж новой) | E62: МОНТАЖ-ДВЕРИ-ВХОД | F62: услуга | G62: 1 | H62: 9000 | I62: =G62*H62 | J62: Андрей (монтаж дверей) | K62: =HYPERLINK("https://www.avito.ru/tula/predlozheniya_uslug?q=установка+входных+дверей", "Открыть ↗")
A63: 22 | B63: Электрика | C63: Работы | D63: Электромонтажные работы под ключ (разводка 32 точек, штробы, щит, счётчик) | E63: РАБОТА-ЭЛЕКТРИКА-32 | F63: договор | G63: 1 | H63: 50000 | I63: =G63*H63 | J63: Анатолий Кушнарев (бригада) | K63: =HYPERLINK("https://www.avito.ru/tula/predlozheniya_uslug?q=электромонтаж+квартиры+под+ключ", "Открыть ↗")
A64: 24 | B64: Демонтаж | C64: Работы | D64: Зачистка стен/потолка (обои, плитка в зале и спальне), вынос мусора, 1-й слой грунта | E64: ДЕМОНТАЖ-ЗАЧИСТКА-2 | F64: смена | G64: 1 | H64: 15000 | I64: =G64*H64 | J64: Бригада разнорабочих | K64: =HYPERLINK("https://www.avito.ru/tula/predlozheniya_uslug?q=зачистка+стен+демонтаж+обоев", "Открыть ↗")
A65: 40 | B65: Логистика | C65: Доставка | D65: Грузовое такси / Доставка закупки материалов и сантехники (Лемана — Фрунзе 17) | E65: ГРУЗОТАКСИ-ЛЕРОЙ | F65: рейс | G65: 1 | H65: 2100 | I65: =G65*H65 | J65: Грузовое такси / Перевозка | K65: =HYPERLINK("https://www.avito.ru/tula/predlozheniya_uslug?q=грузоперевозки+грузовое+такси", "Открыть ↗")
A66: 41 | B66: Демонтаж | C66: Работы | D66: Погрузка в Лемана ПРО, разгрузка и подъём на 5 этаж + демонтаж плитки пола с/у | E66: ПОДЪЕМ-ДЕМОНТАЖ-СУ | F66: смена | G66: 1 | H66: 15000 | I66: =G66*H66 | J66: Бригада грузчиков / Разнорабочие | K66: =HYPERLINK("https://www.avito.ru/tula/predlozheniya_uslug?q=подъем+стройматериалов+на+этаж+грузчики", "Открыть ↗")
A67: 42 | B67: Черновые стены | C67: Отделочные работы | D67: Штукатурка (69 м² по 500 ₽) и шпаклёвка стен White Box (106 м² по 500 ₽) | E67: ОТДЕЛКА-СТЕН-ЕЛЕНА | F67: комплекс | G67: 1 | H67: 87500 | I67: =G67*H67 | J67: Елена (мастер-отделочник) | K67: =HYPERLINK("https://www.avito.ru/tula/predlozheniya_uslug?q=штукатурка+шпаклевка+стен", "Открыть ↗")
A68: 48 | B68: Санузел | C68: Сантехника / Работы | D68: Срезка полотенцесушителя и нарезка трубной резьбы на отводах стояка | E68: РАБОТА-САНТЕХ-СУШ | F68: услуга | G68: 1 | H68: 3000 | I68: =G68*H68 | J68: Вадим (сантехник УК) / Сантехник | K68: =HYPERLINK("https://www.avito.ru/tula/predlozheniya_uslug?q=сантехник+срезка+полотенцесушителя", "Открыть ↗")
A69: 49 | B69: Логистика | C69: Доставка | D69: Такси (оперативная доставка материалов и инструмента из Лемана ПРО на объект) | E69: ТАКСИ-ЛЕРОЙ-ОБЪЕКТ | F69: рейс | G69: 1 | H69: 1000 | I69: =G69*H69 | J69: Такси (Яндекс Go) | K69: =HYPERLINK("https://www.avito.ru/tula/predlozheniya_uslug?q=такси+доставка+курьер", "Открыть ↗")
A70: 60 | B70: Логистика | C70: Доставка | D70: Такси (оперативная доставка / подвоз материалов на объект) | E70: ТАКСИ-ДОСТАВКА-2 | F70: рейс | G70: 1 | H70: 850 | I70: =G70*H70 | J70: Такси (Яндекс Go) | K70: =HYPERLINK("https://www.avito.ru/tula/predlozheniya_uslug?q=такси+доставка+курьер", "Открыть ↗")
A71: 61 | B71: Санузел | C71: Плиточные работы | D71: Работы плиточника (аванс / подготовка к укладке плитки в санузле) | E71: РАБОТА-ПЛИТОЧНИК-1 | F71: аванс | G71: 1 | H71: 1700 | I71: =G71*H71 | J71: Плиточник (мастер) | K71: =HYPERLINK("https://www.avito.ru/tula/predlozheniya_uslug?q=плиточник+укладка+плитки", "Открыть ↗")
A72: 62 | B72: Санузел | C72: Стяжка пола | D72: Работы плиточника: заливка стяжки пола в санузле/туалете | E72: СТЯЖКА-ПОЛА-СУ | F72: услуга | G72: 1 | H72: 3300 | I72: =G72*H72 | J72: Плиточник (мастер) | K72: =HYPERLINK("https://www.avito.ru/tula/predlozheniya_uslug?q=стяжка+пола+санузел", "Открыть ↗")
A73: 63 | B73: Санузел | C73: Штукатурка стен | D73: Оплата за штукатурку туалета (санузла) под 90° под ванну и плитку | E73: ШТУКАТУРКА-СУ-90 | F73: комплекс | G73: 1 | H73: 13400 | I73: =G73*H73 | J73: Елена (мастер-отделочник) | K73: =HYPERLINK("https://www.avito.ru/tula/predlozheniya_uslug?q=штукатурка+санузла+под+90", "Открыть ↗")
A74: 68 | B74: Санузел | C74: Сантехнические работы | D74: Работы сантехников (разводка/монтаж узлов водоснабжения и канализации) | E74: РАБОТА-САНТЕХ-РАЗВОДКА | F74: комплекс | G74: 1 | H74: 3000 | I74: =G74*H74 | J74: Сантехники (мастера) | K74: =HYPERLINK("https://www.avito.ru/tula/predlozheniya_uslug?q=разводка+труб+сантехника", "Открыть ↗")
A75: 71 | B75: Логистика | C75: Доставка | D75: Такси (оперативная доставка / подвоз материалов на объект ул. Фрунзе 17) | E75: ТАКСИ-ОБЪЕКТ-3 | F75: рейс | G75: 1 | H75: 1050 | I75: =G75*H75 | J75: Такси | K75: =HYPERLINK("https://taxi.yandex.ru/", "Открыть ↗")
A76: 74 | B76: Санузел / Кухня | C76: Плиточные работы | D76: Работы плиточника: укладка плитки в санузле, фартук на кухне, фартук ванной из плитки, лючки на магнитах, отверстия под розетки | E76: РАБОТА-ПЛИТОЧНИК-ФИНАЛ | F76: комплекс | G76: 1 | H76: 86000 | I76: =G76*H76 | J76: Плиточник (мастер) | K76: =HYPERLINK("https://www.avito.ru/tula/predlozheniya_uslug?q=укладка+плитки+санузел", "Открыть ↗")
A77: 78 | B77: Логистика | C77: Доставка | D77: Такси (оперативная поездка по объекту) | E77: ТАКСИ-ОБЪЕКТ-4 | F77: рейс | G77: 1 | H77: 700 | I77: =G77*H77 | J77: Такси | K77: =HYPERLINK("https://www.avito.ru/tula/predlozheniya_uslug?q=такси", "Открыть ↗")
B78: ИТОГО РАБОТЫ И ЛОГИСТИКА: | I78: =SUM(I58:I77)
B79: 🏛 БЛОК 4: ЮРИДИЧЕСКИЕ РАСХОДЫ, ПОШЛИНЫ, ГАЗ, ЭНЕРГОСБЫТ И IT (10 ПОЗИЦИЙ)
A80: 1 | B80: Юр. оформление | C80: Торги | D80: Выпуск квалифицированной ЭЦП (электронная цифровая подпись) | E80: ЭЦП-КОНТУР | F80: шт. | G80: 1 | H80: 7000 | I80: =G80*H80 | J80: УЦ / Контур | K80: =HYPERLINK("https://ca.kontur.ru/", "Открыть ↗")
A81: 2 | B81: Юр. оформление | C81: Росреестр | D81: Государственная пошлина (регистрация перехода права собственности) | E81: ГОСПОШЛИНА-ПРАВО | F81: платеж | G81: 1 | H81: 5000 | I81: =G81*H81 | J81: Росреестр | K81: =HYPERLINK("https://rosreestr.gov.ru/", "Открыть ↗")
A82: 10 | B82: IT / AI | C82: Инфраструктура | D82: Пополнение баланса OpenRouter (AI-ассистент Hermes) — транш 1 | E82: OPENROUTER-TRANS-1 | F82: платёж | G82: 1 | H82: 3000 | I82: =G82*H82 | J82: OpenRouter | K82: =HYPERLINK("https://openrouter.ai/", "Открыть ↗")
A83: 12 | B83: Газ | C83: Безопасность | D83: Акт ВДПО — проверка дымохода и вентканала | E83: ВДПО-АКТ-ВЕНТ | F83: акт | G83: 1 | H83: 1500 | I83: =G83*H83 | J83: ВДПО / Газовая служба | K83: =HYPERLINK("https://vdpo71.ru/", "Открыть ↗")
A84: 13 | B84: Газ | C84: Коммуналка | D84: Оплата квитанций Тулагоргаз (платежки/техобслуживание) | E84: ТУЛАГОРГАЗ-КВИТАНЦИЯ | F84: платеж | G84: 1 | H84: 800 | I84: =G84*H84 | J84: Тулагоргаз | K84: =HYPERLINK("https://tulagorgaz.ru/", "Открыть ↗")
A85: 21 | B85: Энергосбыт | C85: Учёт | D85: Срочный выезд инспектора ТНС энерго Тула (снятие пломбы со старого счётчика) | E85: ТНС-ВЫЕЗД-ПЛОМБА | F85: услуга | G85: 1 | H85: 2500 | I85: =G85*H85 | J85: АО "ТНС энерго Тула" | K85: =HYPERLINK("https://tns-e.ru/", "Открыть ↗")
A86: 31 | B86: IT / AI | C86: Инфраструктура | D86: Пополнение баланса OpenRouter (AI-ассистент Hermes) — транш 2 | E86: OPENROUTER-TRANS-2 | F86: платёж | G86: 1 | H86: 2500 | I86: =G86*H86 | J86: OpenRouter | K86: =HYPERLINK("https://openrouter.ai/", "Открыть ↗")
A87: 33 | B87: Энергосбыт | C87: Учёт | D87: Дистанционная распломбировка старого электросчётчика (согласование) | E87: ТНС-РАСПЛОМБ-ДИСТ | F87: услуга | G87: 1 | H87: 2200 | I87: =G87*H87 | J87: ТНС энерго Тула / Энергосбыт | K87: =HYPERLINK("https://tns-e.ru/", "Открыть ↗")
A88: 69 | B88: Газ | C88: Работы и материалы | D88: Работы газовщика: перенос / срезка / перемонтаж газовой трубы на кухне | E88: ГАЗ-ПЕРЕНОС-ТРУБА | F88: комплекс | G88: 1 | H88: 7300 | I88: =G88*H88 | J88: Газовщик (мастер / горгаз) | K88: =HYPERLINK("https://www.avito.ru/tula/predlozheniya_uslug?q=перенос+газовой+трубы", "Открыть ↗")
A89: 72 | B89: Безопасность | C89: Доступ | D89: Ключи от домофона (дубликаты для мастеров и объекта) | E89: КЛЮЧИ-ДОМОФОН-3 | F89: компл. | G89: 1 | H89: 500 | I89: =G89*H89 | J89: Изготовление ключей | K89: =HYPERLINK("https://www.avito.ru/tula/predlozheniya_uslug?q=%D0%B8%D0%B7%D0%B3%D0%BE%D1%82%D0%BE%D0%B2%D0%BB%D0%B5%D0%BD%D0%B8%D0%B5+%D0%BA%D0%BB%D1%8E%D1%87%D0%B5%D0%B9+%D0%B4%D0%BE%D0%BC%D0%BE%D1%84%D0%BE%D0%BD", "Открыть ↗")
B90: ИТОГО ЮР. РАСХОДЫ, СЛУЖБЫ И IT: | I90: =SUM(I80:I89)
B91: ОБЩИЙ ИТОГО ФАКТ РАСХОДОВ (ДИНАМИЧЕСКИЙ): | I91: =SUM(I33, I56, I78, I90)
